llm_connectors/__init__.py
llm_connectors/_version.py
llm_connectors/base.py
llm_connectors/chatgpt.py
llm_connectors/copilot.py
llm_connectors/deepseek.py
llm_connectors/gemini.py
llm_connectors-0.1.0.dist-info/METADATA
llm_connectors-0.1.0.dist-info/WHEEL
llm_connectors-0.1.0.dist-info/licenses/LICENSE
llm_connectors-0.1.0.dist-info/RECORD
